MANIFEST.in
README.rst
setup.py
docs/HISTORY.txt
docs/LICENSE.GPL
docs/LICENSE.txt
ftw/__init__.py
ftw.dashboard.portlets.recentlymodified.egg-info/PKG-INFO
ftw.dashboard.portlets.recentlymodified.egg-info/SOURCES.txt
ftw.dashboard.portlets.recentlymodified.egg-info/dependency_links.txt
ftw.dashboard.portlets.recentlymodified.egg-info/entry_points.txt
ftw.dashboard.portlets.recentlymodified.egg-info/namespace_packages.txt
ftw.dashboard.portlets.recentlymodified.egg-info/not-zip-safe
ftw.dashboard.portlets.recentlymodified.egg-info/requires.txt
ftw.dashboard.portlets.recentlymodified.egg-info/top_level.txt
ftw/dashboard/__init__.py
ftw/dashboard/portlets/__init__.py
ftw/dashboard/portlets/recentlymodified/__init__.py
ftw/dashboard/portlets/recentlymodified/configure.zcml
ftw/dashboard/portlets/recentlymodified/recentlymodified.truncate-long-text.js
ftw/dashboard/portlets/recentlymodified/testing.py
ftw/dashboard/portlets/recentlymodified/browser/__init__.py
ftw/dashboard/portlets/recentlymodified/browser/configure.zcml
ftw/dashboard/portlets/recentlymodified/browser/recentlymodified.py
ftw/dashboard/portlets/recentlymodified/browser/templates/quick_preview.pt
ftw/dashboard/portlets/recentlymodified/browser/templates/recently_modified_view.pt
ftw/dashboard/portlets/recentlymodified/browser/templates/recentlymodified.pt
ftw/dashboard/portlets/recentlymodified/locales/ftw.dashboard.portlets.recentlymodified.pot
ftw/dashboard/portlets/recentlymodified/locales/plone.pot
ftw/dashboard/portlets/recentlymodified/locales/de/LC_MESSAGES/ftw.dashboard.portlets.recentlymodified.po
ftw/dashboard/portlets/recentlymodified/locales/de/LC_MESSAGES/plone.po
ftw/dashboard/portlets/recentlymodified/locales/fr/LC_MESSAGES/ftw.dashboard.portlets.recentlymodified.po
ftw/dashboard/portlets/recentlymodified/locales/fr/LC_MESSAGES/plone.po
ftw/dashboard/portlets/recentlymodified/profiles/default/actions.xml
ftw/dashboard/portlets/recentlymodified/profiles/default/cssregistry.xml
ftw/dashboard/portlets/recentlymodified/profiles/default/jsregistry.xml
ftw/dashboard/portlets/recentlymodified/profiles/default/metadata.xml
ftw/dashboard/portlets/recentlymodified/profiles/default/portlets.xml
ftw/dashboard/portlets/recentlymodified/profiles/default/propertiestool.xml
ftw/dashboard/portlets/recentlymodified/profiles/default/registry.xml
ftw/dashboard/portlets/recentlymodified/resources/recentlymodified.css
ftw/dashboard/portlets/recentlymodified/tests/__init__.py
