Metadata-Version: 1.1
Name: ftw.dashboard.portlets.recentlymodified
Version: 1.3.1
Summary: Recently modified portlet for the dashboard
Home-page: https://github.com/4teamwork/ftw.dashboard.portlets.recentlymodified
Author: Philipp Gross
Author-email: mailto:info@4teamwork.ch
License: GPL2
Keywords: ftw dashboard portlet recentlymodified
Platform: UNKNOWN
Classifier: Framework :: Plone
Classifier: Framework :: Plone :: 4.1
Classifier: Framework :: Plone :: 4.2
Classifier: Programming Language :: Python
Classifier: Topic :: Software Development :: Libraries :: Python Modules
